standardize_it/__init__.py
standardize_it/standardize_it.py
python_standardize_it-1.0.2.dist-info/LICENSE
python_standardize_it-1.0.2.dist-info/METADATA
python_standardize_it-1.0.2.dist-info/WHEEL
python_standardize_it-1.0.2.dist-info/top_level.txt
python_standardize_it-1.0.2.dist-info/RECORD
