Metadata-Version: 2.1
Name: python-standardize-it
Version: 1.0.2
Summary: Tool for standardizing strings against a known set of standards
License: GNU General Public License v3 (GPLv3)
Keywords: NLP,strings,standardizing,standardization,normalization,cosine,similarity
Classifier: Development Status :: 5 - Production/Stable
Classifier: Intended Audience :: Developers
Classifier: License :: OSI Approved :: GNU General Public License v3 (GPLv3)
Classifier: Natural Language :: English
Classifier: Programming Language :: Python :: 3.9
Classifier: Topic :: Software Development :: Libraries :: Python Modules
Classifier: Topic :: Software Development :: Pre-processors
Classifier: Topic :: Text Processing :: General
Classifier: Topic :: Utilities
License-File: LICENSE
